[
  {
    "matchId": 15141774,
    "date": "2025-11-26",
    "season": "Eliteserien 2025",
    "round": 2,
    "venue": "away",
    "opponent": "Aalesunds FK",
    "opponentId": 677,
    "score": "3-1",
    "htScore": "0-1",
    "result": "L",
    "goalsFor": 1,
    "goalsAgainst": 3,
    "formation": "5-3-2",
    "opponentFormation": "5-3-2",
    "stats": {
      "ALL": {
        "xg": 0.78,
        "shots": 13,
        "shotsOnTarget": 3,
        "shotsOffTarget": 4,
        "blockedShots": 6,
        "possession": 40,
        "corners": 4,
        "offsides": 0,
        "fouls": 15,
        "yellowCards": 3,
        "redCards": 0,
        "passes": 446,
        "accuratePasses": 359,
        "saves": 11
      }
    },
    "opponentStats": {
      "ALL": {
        "xg": 3.98,
        "shots": 31,
        "shotsOnTarget": 14,
        "shotsOffTarget": 9,
        "blockedShots": 8,
        "possession": 60,
        "corners": 17,
        "offsides": 2,
        "fouls": 17,
        "yellowCards": 3,
        "redCards": 0,
        "passes": 690,
        "accuratePasses": 573,
        "saves": 2
      }
    },
    "players": [
      {
        "name": "Andreas Hermansen",
        "position": "G",
        "jersey": 1,
        "isSub": false,
        "minutes": 120,
        "rating": null,
        "goals": 0,
        "assists": 0,
        "shots": 0,
        "shotsOnTarget": 0,
        "passes": 33,
        "accuratePasses": 25,
        "touches": 43,
        "xg": 0,
        "xa": 0
      },
      {
        "name": "Herman Kleppa",
        "position": "D",
        "jersey": 2,
        "isSub": false,
        "minutes": 118,
        "rating": null,
        "goals": 0,
        "assists": 0,
        "shots": 1,
        "shotsOnTarget": 0,
        "passes": 37,
        "accuratePasses": 34,
        "touches": 68,
        "xg": 0.02,
        "xa": 0
      },
      {
        "name": "Nicolas Pignatel Jenssen",
        "position": "D",
        "jersey": 5,
        "isSub": false,
        "minutes": 29,
        "rating": null,
        "goals": 0,
        "assists": 0,
        "shots": 0,
        "shotsOnTarget": 0,
        "passes": 12,
        "accuratePasses": 12,
        "touches": 14,
        "xg": 0,
        "xa": 0
      },
      {
        "name": "Isak Jönsson",
        "position": "D",
        "jersey": 31,
        "isSub": false,
        "minutes": 120,
        "rating": null,
        "goals": 0,
        "assists": 0,
        "shots": 0,
        "shotsOnTarget": 0,
        "passes": 42,
        "accuratePasses": 37,
        "touches": 65,
        "xg": 0,
        "xa": 0.01
      },
      {
        "name": "Bjørn Mæland",
        "position": "D",
        "jersey": 3,
        "isSub": false,
        "minutes": 120,
        "rating": null,
        "goals": 0,
        "assists": 0,
        "shots": 0,
        "shotsOnTarget": 0,
        "passes": 55,
        "accuratePasses": 47,
        "touches": 72,
        "xg": 0,
        "xa": 0
      },
      {
        "name": "Kristian Kjeverud Eggen",
        "position": "D",
        "jersey": 21,
        "isSub": false,
        "minutes": 93,
        "rating": null,
        "goals": 0,
        "assists": 0,
        "shots": 0,
        "shotsOnTarget": 0,
        "passes": 17,
        "accuratePasses": 13,
        "touches": 27,
        "xg": 0,
        "xa": 0
      },
      {
        "name": "Horenus Zewdu Tadesse",
        "position": "M",
        "jersey": 22,
        "isSub": false,
        "minutes": 106,
        "rating": null,
        "goals": 0,
        "assists": 0,
        "shots": 0,
        "shotsOnTarget": 0,
        "passes": 19,
        "accuratePasses": 16,
        "touches": 33,
        "xg": 0,
        "xa": 0.02
      },
      {
        "name": "Chris Sleveland",
        "position": "M",
        "jersey": 8,
        "isSub": false,
        "minutes": 120,
        "rating": null,
        "goals": 0,
        "assists": 0,
        "shots": 2,
        "shotsOnTarget": 0,
        "passes": 71,
        "accuratePasses": 58,
        "touches": 83,
        "xg": 0.01,
        "xa": 0
      },
      {
        "name": "Scott Vatne",
        "position": "M",
        "jersey": 27,
        "isSub": false,
        "minutes": 106,
        "rating": null,
        "goals": 0,
        "assists": 0,
        "shots": 1,
        "shotsOnTarget": 1,
        "passes": 27,
        "accuratePasses": 25,
        "touches": 40,
        "xg": 0.05,
        "xa": 0.09
      },
      {
        "name": "Franklin Nyenetue",
        "position": "F",
        "jersey": 77,
        "isSub": false,
        "minutes": 68,
        "rating": null,
        "goals": 0,
        "assists": 0,
        "shots": 1,
        "shotsOnTarget": 0,
        "passes": 11,
        "accuratePasses": 8,
        "touches": 26,
        "xg": 0.05,
        "xa": 0.46
      },
      {
        "name": "Oscar Kapskarmo",
        "position": "F",
        "jersey": 9,
        "isSub": false,
        "minutes": 120,
        "rating": null,
        "goals": 1,
        "assists": 0,
        "shots": 3,
        "shotsOnTarget": 1,
        "passes": 21,
        "accuratePasses": 13,
        "touches": 58,
        "xg": 0.52,
        "xa": 0
      },
      {
        "name": "Sammi Davis",
        "position": "D",
        "jersey": 91,
        "isSub": true,
        "minutes": 106,
        "rating": null,
        "goals": 0,
        "assists": 0,
        "shots": 0,
        "shotsOnTarget": 0,
        "passes": 47,
        "accuratePasses": 32,
        "touches": 61,
        "xg": 0,
        "xa": 0
      },
      {
        "name": "Mathias Sauer",
        "position": "F",
        "jersey": 45,
        "isSub": true,
        "minutes": 67,
        "rating": null,
        "goals": 0,
        "assists": 0,
        "shots": 3,
        "shotsOnTarget": 0,
        "passes": 16,
        "accuratePasses": 12,
        "touches": 32,
        "xg": 0.1,
        "xa": 0.03
      },
      {
        "name": "Paya Pichkah",
        "position": "D",
        "jersey": 13,
        "isSub": true,
        "minutes": 42,
        "rating": null,
        "goals": 0,
        "assists": 0,
        "shots": 0,
        "shotsOnTarget": 0,
        "passes": 20,
        "accuratePasses": 13,
        "touches": 28,
        "xg": 0,
        "xa": 0
      },
      {
        "name": "Martin Haheim-Elveseter",
        "position": "M",
        "jersey": 29,
        "isSub": true,
        "minutes": 29,
        "rating": null,
        "goals": 0,
        "assists": 0,
        "shots": 2,
        "shotsOnTarget": 1,
        "passes": 8,
        "accuratePasses": 7,
        "touches": 22,
        "xg": 0.03,
        "xa": 0
      },
      {
        "name": "Samuel Adegbenro",
        "position": "M",
        "jersey": 19,
        "isSub": true,
        "minutes": 29,
        "rating": null,
        "goals": 0,
        "assists": 0,
        "shots": 0,
        "shotsOnTarget": 0,
        "passes": 5,
        "accuratePasses": 4,
        "touches": 11,
        "xg": 0,
        "xa": 0
      },
      {
        "name": "Adrian Rogulj",
        "position": "F",
        "jersey": 14,
        "isSub": true,
        "minutes": 17,
        "rating": null,
        "goals": 0,
        "assists": 0,
        "shots": 0,
        "shotsOnTarget": 0,
        "passes": 3,
        "accuratePasses": 2,
        "touches": 5,
        "xg": 0,
        "xa": 0
      },
      {
        "name": "Sander Åke Andreas Lønning",
        "position": "G",
        "jersey": 12,
        "isSub": true,
        "minutes": null,
        "rating": null,
        "goals": 0,
        "assists": 0,
        "shots": null,
        "shotsOnTarget": null,
        "passes": null,
        "accuratePasses": null,
        "touches": null,
        "xg": null,
        "xa": null
      },
      {
        "name": "Phillip Hovland",
        "position": "D",
        "jersey": 18,
        "isSub": true,
        "minutes": null,
        "rating": null,
        "goals": 0,
        "assists": 0,
        "shots": null,
        "shotsOnTarget": null,
        "passes": null,
        "accuratePasses": null,
        "touches": null,
        "xg": null,
        "xa": null
      },
      {
        "name": "Árni Nóa Atlason",
        "position": "M",
        "jersey": 30,
        "isSub": true,
        "minutes": null,
        "rating": null,
        "goals": 0,
        "assists": 0,
        "shots": null,
        "shotsOnTarget": null,
        "passes": null,
        "accuratePasses": null,
        "touches": null,
        "xg": null,
        "xa": null
      }
    ],
    "incidents": [
      {
        "minute": 120,
        "addedTime": 1,
        "type": "substitution",
        "klass": "regular",
        "player": "Elias Heggland Myrlid",
        "assist": "Paul Ngongo Iversen",
        "team": "home",
        "isThisTeam": false
      },
      {
        "minute": 119,
        "addedTime": null,
        "type": "goal",
        "klass": "regular",
        "player": "Davíð Snær Jóhannsson",
        "assist": "Mathias Christensen",
        "team": "home",
        "isThisTeam": false
      },
      {
        "minute": 106,
        "addedTime": null,
        "type": "substitution",
        "klass": "regular",
        "player": "Adrian Rogulj",
        "assist": "Herman Kleppa",
        "team": "away",
        "isThisTeam": true
      },
      {
        "minute": 97,
        "addedTime": null,
        "type": "card",
        "klass": "yellow",
        "player": "Aleksander Kjelsen",
        "assist": null,
        "team": "home",
        "isThisTeam": false
      },
      {
        "minute": 97,
        "addedTime": null,
        "type": "substitution",
        "klass": "regular",
        "player": "Marius Andresen",
        "assist": "Kristian Lonebu",
        "team": "home",
        "isThisTeam": false
      },
      {
        "minute": 97,
        "addedTime": null,
        "type": "substitution",
        "klass": "regular",
        "player": "Philip Sandvik Aukland",
        "assist": "Henrik Melland",
        "team": "home",
        "isThisTeam": false
      },
      {
        "minute": 96,
        "addedTime": null,
        "type": "substitution",
        "klass": "regular",
        "player": "Martin Haheim-Elveseter",
        "assist": "Horenus Zewdu Tadesse",
        "team": "away",
        "isThisTeam": true
      },
      {
        "minute": 96,
        "addedTime": null,
        "type": "substitution",
        "klass": "regular",
        "player": "Samuel Adegbenro",
        "assist": "Scott Vatne",
        "team": "away",
        "isThisTeam": true
      },
      {
        "minute": 92,
        "addedTime": null,
        "type": "goal",
        "klass": "regular",
        "player": "Frederik Heiselberg",
        "assist": "Mathias Christensen",
        "team": "home",
        "isThisTeam": false
      },
      {
        "minute": 90,
        "addedTime": 4,
        "type": "card",
        "klass": "yellow",
        "player": "Jakob Nyland Örsahl",
        "assist": null,
        "team": "home",
        "isThisTeam": false
      },
      {
        "minute": 90,
        "addedTime": 1,
        "type": "goal",
        "klass": "regular",
        "player": "Kristian Lonebu",
        "assist": null,
        "team": "home",
        "isThisTeam": false
      },
      {
        "minute": 90,
        "addedTime": null,
        "type": "substitution",
        "klass": "regular",
        "player": "Paya Pichkah",
        "assist": "Kristian Kjeverud Eggen",
        "team": "away",
        "isThisTeam": true
      },
      {
        "minute": 87,
        "addedTime": null,
        "type": "card",
        "klass": "yellow",
        "player": "Mathias Christensen",
        "assist": null,
        "team": "home",
        "isThisTeam": false
      },
      {
        "minute": 82,
        "addedTime": null,
        "type": "card",
        "klass": "yellow",
        "player": "Andreas Hermansen",
        "assist": null,
        "team": "away",
        "isThisTeam": true
      },
      {
        "minute": 77,
        "addedTime": null,
        "type": "substitution",
        "klass": "regular",
        "player": "Davíð Snær Jóhannsson",
        "assist": "Nikolai Skuseth",
        "team": "home",
        "isThisTeam": false
      },
      {
        "minute": 77,
        "addedTime": null,
        "type": "substitution",
        "klass": "regular",
        "player": "Frederik Heiselberg",
        "assist": "Kristoffer Nessø",
        "team": "home",
        "isThisTeam": false
      },
      {
        "minute": 65,
        "addedTime": null,
        "type": "substitution",
        "klass": "regular",
        "player": "Mathias Sauer",
        "assist": "Franklin Nyenetue",
        "team": "away",
        "isThisTeam": true
      },
      {
        "minute": 46,
        "addedTime": null,
        "type": "card",
        "klass": "yellow",
        "player": "Sammi Davis",
        "assist": null,
        "team": "away",
        "isThisTeam": true
      },
      {
        "minute": 33,
        "addedTime": null,
        "type": "card",
        "klass": "yellow",
        "player": "Chris Sleveland",
        "assist": null,
        "team": "away",
        "isThisTeam": true
      },
      {
        "minute": 30,
        "addedTime": null,
        "type": "substitution",
        "klass": "regular",
        "player": "Sammi Davis",
        "assist": "Nicolas Pignatel Jenssen",
        "team": "away",
        "isThisTeam": true
      },
      {
        "minute": 8,
        "addedTime": null,
        "type": "goal",
        "klass": "regular",
        "player": "Oscar Kapskarmo",
        "assist": null,
        "team": "away",
        "isThisTeam": true
      }
    ]
  },
  {
    "matchId": 15032938,
    "date": "2025-11-22",
    "season": "Eliteserien 2025",
    "round": 1,
    "venue": "home",
    "opponent": "Ranheim IL",
    "opponentId": 708,
    "score": "3-2",
    "htScore": "1-1",
    "result": "W",
    "goalsFor": 3,
    "goalsAgainst": 2,
    "formation": "5-3-2",
    "opponentFormation": "4-4-2",
    "stats": {
      "ALL": {
        "xg": 0.91,
        "shots": 14,
        "shotsOnTarget": 7,
        "shotsOffTarget": 4,
        "blockedShots": 2,
        "possession": 37,
        "corners": 5,
        "offsides": 1,
        "fouls": 8,
        "yellowCards": 2,
        "redCards": 0,
        "passes": 352,
        "accuratePasses": 280,
        "saves": 6
      }
    },
    "opponentStats": {
      "ALL": {
        "xg": 2.31,
        "shots": 19,
        "shotsOnTarget": 8,
        "shotsOffTarget": 4,
        "blockedShots": 7,
        "possession": 63,
        "corners": 9,
        "offsides": 2,
        "fouls": 11,
        "yellowCards": 2,
        "redCards": 0,
        "passes": 630,
        "accuratePasses": 536,
        "saves": 4
      }
    },
    "players": [
      {
        "name": "Andreas Hermansen",
        "position": "G",
        "jersey": 1,
        "isSub": false,
        "minutes": 90,
        "rating": null,
        "goals": 0,
        "assists": 0,
        "shots": 0,
        "shotsOnTarget": 0,
        "passes": 26,
        "accuratePasses": 25,
        "touches": 34,
        "xg": 0,
        "xa": 0
      },
      {
        "name": "Herman Kleppa",
        "position": "D",
        "jersey": 2,
        "isSub": false,
        "minutes": 90,
        "rating": null,
        "goals": 0,
        "assists": 0,
        "shots": 0,
        "shotsOnTarget": 0,
        "passes": 17,
        "accuratePasses": 11,
        "touches": 28,
        "xg": 0,
        "xa": 0
      },
      {
        "name": "Nicolas Pignatel Jenssen",
        "position": "D",
        "jersey": 5,
        "isSub": false,
        "minutes": 90,
        "rating": null,
        "goals": 0,
        "assists": 0,
        "shots": 0,
        "shotsOnTarget": 0,
        "passes": 34,
        "accuratePasses": 29,
        "touches": 38,
        "xg": 0,
        "xa": 0
      },
      {
        "name": "Isak Jönsson",
        "position": "D",
        "jersey": 31,
        "isSub": false,
        "minutes": 90,
        "rating": null,
        "goals": 0,
        "assists": 0,
        "shots": 0,
        "shotsOnTarget": 0,
        "passes": 46,
        "accuratePasses": 38,
        "touches": 50,
        "xg": 0,
        "xa": 0
      },
      {
        "name": "Bjørn Mæland",
        "position": "D",
        "jersey": 3,
        "isSub": false,
        "minutes": 79,
        "rating": null,
        "goals": 0,
        "assists": 0,
        "shots": 0,
        "shotsOnTarget": 0,
        "passes": 36,
        "accuratePasses": 27,
        "touches": 47,
        "xg": 0,
        "xa": 0.01
      },
      {
        "name": "Scott Vatne",
        "position": "D",
        "jersey": 27,
        "isSub": false,
        "minutes": 90,
        "rating": null,
        "goals": 1,
        "assists": 0,
        "shots": 3,
        "shotsOnTarget": 2,
        "passes": 34,
        "accuratePasses": 28,
        "touches": 58,
        "xg": 0.16,
        "xa": 0
      },
      {
        "name": "Chris Sleveland",
        "position": "M",
        "jersey": 8,
        "isSub": false,
        "minutes": 90,
        "rating": null,
        "goals": 0,
        "assists": 0,
        "shots": 3,
        "shotsOnTarget": 0,
        "passes": 46,
        "accuratePasses": 40,
        "touches": 60,
        "xg": 0.06,
        "xa": 0.08
      },
      {
        "name": "Paya Pichkah",
        "position": "M",
        "jersey": 13,
        "isSub": false,
        "minutes": 65,
        "rating": null,
        "goals": 0,
        "assists": 0,
        "shots": 1,
        "shotsOnTarget": 0,
        "passes": 34,
        "accuratePasses": 27,
        "touches": 47,
        "xg": 0.05,
        "xa": 0
      },
      {
        "name": "Horenus Zewdu Tadesse",
        "position": "M",
        "jersey": 22,
        "isSub": false,
        "minutes": 90,
        "rating": null,
        "goals": 0,
        "assists": 0,
        "shots": 1,
        "shotsOnTarget": 1,
        "passes": 23,
        "accuratePasses": 19,
        "touches": 42,
        "xg": 0.1,
        "xa": 0.06
      },
      {
        "name": "Mathias Sauer",
        "position": "F",
        "jersey": 45,
        "isSub": false,
        "minutes": 89,
        "rating": null,
        "goals": 1,
        "assists": 0,
        "shots": 3,
        "shotsOnTarget": 2,
        "passes": 16,
        "accuratePasses": 8,
        "touches": 32,
        "xg": 0.21,
        "xa": 0
      },
      {
        "name": "Oscar Kapskarmo",
        "position": "F",
        "jersey": 9,
        "isSub": false,
        "minutes": 90,
        "rating": null,
        "goals": 1,
        "assists": 0,
        "shots": 2,
        "shotsOnTarget": 2,
        "passes": 22,
        "accuratePasses": 14,
        "touches": 47,
        "xg": 0.17,
        "xa": 0.15
      },
      {
        "name": "Kristian Kjeverud Eggen",
        "position": "D",
        "jersey": 21,
        "isSub": true,
        "minutes": 34,
        "rating": null,
        "goals": 0,
        "assists": 0,
        "shots": 0,
        "shotsOnTarget": 0,
        "passes": 9,
        "accuratePasses": 6,
        "touches": 17,
        "xg": 0,
        "xa": 0.15
      },
      {
        "name": "Franklin Nyenetue",
        "position": "F",
        "jersey": 77,
        "isSub": true,
        "minutes": 20,
        "rating": null,
        "goals": 0,
        "assists": 1,
        "shots": 1,
        "shotsOnTarget": 0,
        "passes": 3,
        "accuratePasses": 3,
        "touches": 5,
        "xg": 0.15,
        "xa": 0.12
      },
      {
        "name": "Martin Haheim-Elveseter",
        "position": "M",
        "jersey": 29,
        "isSub": true,
        "minutes": 10,
        "rating": null,
        "goals": 0,
        "assists": 0,
        "shots": 0,
        "shotsOnTarget": 0,
        "passes": 5,
        "accuratePasses": 4,
        "touches": 10,
        "xg": 0,
        "xa": 0
      },
      {
        "name": "Sander Åke Andreas Lønning",
        "position": "G",
        "jersey": 12,
        "isSub": true,
        "minutes": null,
        "rating": null,
        "goals": 0,
        "assists": 0,
        "shots": null,
        "shotsOnTarget": null,
        "passes": null,
        "accuratePasses": null,
        "touches": null,
        "xg": null,
        "xa": null
      },
      {
        "name": "Phillip Hovland",
        "position": "D",
        "jersey": 18,
        "isSub": true,
        "minutes": null,
        "rating": null,
        "goals": 0,
        "assists": 0,
        "shots": null,
        "shotsOnTarget": null,
        "passes": null,
        "accuratePasses": null,
        "touches": null,
        "xg": null,
        "xa": null
      },
      {
        "name": "Sammi Davis",
        "position": "D",
        "jersey": 91,
        "isSub": true,
        "minutes": null,
        "rating": null,
        "goals": 0,
        "assists": 0,
        "shots": null,
        "shotsOnTarget": null,
        "passes": null,
        "accuratePasses": null,
        "touches": null,
        "xg": null,
        "xa": null
      },
      {
        "name": "Árni Nóa Atlason",
        "position": "M",
        "jersey": 30,
        "isSub": true,
        "minutes": null,
        "rating": null,
        "goals": 0,
        "assists": 0,
        "shots": null,
        "shotsOnTarget": null,
        "passes": null,
        "accuratePasses": null,
        "touches": null,
        "xg": null,
        "xa": null
      },
      {
        "name": "Adrian Rogulj",
        "position": "F",
        "jersey": 14,
        "isSub": true,
        "minutes": null,
        "rating": null,
        "goals": 0,
        "assists": 0,
        "shots": null,
        "shotsOnTarget": null,
        "passes": null,
        "accuratePasses": null,
        "touches": null,
        "xg": null,
        "xa": null
      },
      {
        "name": "Samuel Adegbenro",
        "position": "F",
        "jersey": 19,
        "isSub": true,
        "minutes": null,
        "rating": null,
        "goals": 0,
        "assists": 0,
        "shots": null,
        "shotsOnTarget": null,
        "passes": null,
        "accuratePasses": null,
        "touches": null,
        "xg": null,
        "xa": null
      }
    ],
    "incidents": [
      {
        "minute": 90,
        "addedTime": 6,
        "type": "goal",
        "klass": "regular",
        "player": "Scott Vatne",
        "assist": null,
        "team": "home",
        "isThisTeam": true
      },
      {
        "minute": 90,
        "addedTime": 5,
        "type": "card",
        "klass": "yellow",
        "player": "Tage Bjordal Haukeberg",
        "assist": null,
        "team": "away",
        "isThisTeam": false
      },
      {
        "minute": 88,
        "addedTime": null,
        "type": "substitution",
        "klass": "regular",
        "player": "Martin Haheim-Elveseter",
        "assist": "Mathias Sauer",
        "team": "home",
        "isThisTeam": true
      },
      {
        "minute": 87,
        "addedTime": null,
        "type": "substitution",
        "klass": "regular",
        "player": "Mathias Johnsrud Emilsen",
        "assist": "Per Ciljan Skjelbred",
        "team": "away",
        "isThisTeam": false
      },
      {
        "minute": 84,
        "addedTime": null,
        "type": "goal",
        "klass": "regular",
        "player": "Oscar Kapskarmo",
        "assist": "Franklin Nyenetue",
        "team": "home",
        "isThisTeam": true
      },
      {
        "minute": 79,
        "addedTime": null,
        "type": "card",
        "klass": "yellow",
        "player": "Áki Samuelsen",
        "assist": null,
        "team": "away",
        "isThisTeam": false
      },
      {
        "minute": 77,
        "addedTime": null,
        "type": "substitution",
        "klass": "regular",
        "player": "Franklin Nyenetue",
        "assist": "Bjørn Mæland",
        "team": "home",
        "isThisTeam": true
      },
      {
        "minute": 68,
        "addedTime": null,
        "type": "goal",
        "klass": "penalty",
        "player": "Áki Samuelsen",
        "assist": null,
        "team": "away",
        "isThisTeam": false
      },
      {
        "minute": 66,
        "addedTime": null,
        "type": "card",
        "klass": "yellow",
        "player": "Bjørn Mæland",
        "assist": null,
        "team": "home",
        "isThisTeam": true
      },
      {
        "minute": 63,
        "addedTime": null,
        "type": "substitution",
        "klass": "regular",
        "player": "Kristian Kjeverud Eggen",
        "assist": "Paya Pichkah",
        "team": "home",
        "isThisTeam": true
      },
      {
        "minute": 45,
        "addedTime": 2,
        "type": "goal",
        "klass": "regular",
        "player": "Mathias Sauer",
        "assist": null,
        "team": "home",
        "isThisTeam": true
      },
      {
        "minute": 39,
        "addedTime": null,
        "type": "goal",
        "klass": "regular",
        "player": "Mikael Törset Johnsen",
        "assist": "Seydina Mohamed Diop",
        "team": "away",
        "isThisTeam": false
      },
      {
        "minute": 10,
        "addedTime": null,
        "type": "card",
        "klass": "yellow",
        "player": "Isak Jönsson",
        "assist": null,
        "team": "home",
        "isThisTeam": true
      }
    ]
  },
  {
    "matchId": 13147852,
    "date": "2024-11-23",
    "season": "Eliteserien 2024",
    "round": 2,
    "venue": "home",
    "opponent": "Kongsvinger",
    "opponentId": 672,
    "score": "1-2",
    "htScore": "1-2",
    "result": "L",
    "goalsFor": 1,
    "goalsAgainst": 2,
    "formation": "4-1-4-1",
    "opponentFormation": "4-3-3",
    "stats": {
      "ALL": {
        "xg": 0.44,
        "shots": 10,
        "shotsOnTarget": 3,
        "shotsOffTarget": 3,
        "blockedShots": 4,
        "possession": 55,
        "corners": 2,
        "offsides": 1,
        "fouls": 6,
        "yellowCards": 1,
        "redCards": 0,
        "passes": 431,
        "accuratePasses": 355,
        "saves": 0
      }
    },
    "opponentStats": {
      "ALL": {
        "xg": 1.64,
        "shots": 11,
        "shotsOnTarget": 2,
        "shotsOffTarget": 7,
        "blockedShots": 2,
        "possession": 45,
        "corners": 4,
        "offsides": 0,
        "fouls": 19,
        "yellowCards": 2,
        "redCards": 0,
        "passes": 404,
        "accuratePasses": 324,
        "saves": 2
      }
    },
    "players": [
      {
        "name": "Sander Åke Andreas Lønning",
        "position": "G",
        "jersey": 27,
        "isSub": false,
        "minutes": 90,
        "rating": null,
        "goals": 0,
        "assists": 0,
        "shots": 0,
        "shotsOnTarget": 0,
        "passes": 39,
        "accuratePasses": 36,
        "touches": 44,
        "xg": 0,
        "xa": 0
      },
      {
        "name": "Jo Stalesen",
        "position": "D",
        "jersey": 14,
        "isSub": false,
        "minutes": 90,
        "rating": null,
        "goals": 0,
        "assists": 0,
        "shots": 1,
        "shotsOnTarget": 0,
        "passes": 46,
        "accuratePasses": 32,
        "touches": 68,
        "xg": 0.03,
        "xa": 0
      },
      {
        "name": "Tord Johnsen Salte",
        "position": "D",
        "jersey": 6,
        "isSub": false,
        "minutes": 84,
        "rating": null,
        "goals": 0,
        "assists": 0,
        "shots": 1,
        "shotsOnTarget": 1,
        "passes": 60,
        "accuratePasses": 54,
        "touches": 74,
        "xg": 0.19,
        "xa": 0
      },
      {
        "name": "Adne Midtskogen",
        "position": "D",
        "jersey": 2,
        "isSub": false,
        "minutes": 90,
        "rating": null,
        "goals": 0,
        "assists": 0,
        "shots": 0,
        "shotsOnTarget": 0,
        "passes": 72,
        "accuratePasses": 66,
        "touches": 92,
        "xg": 0,
        "xa": 0
      },
      {
        "name": "Robert Williams",
        "position": "D",
        "jersey": 12,
        "isSub": false,
        "minutes": 84,
        "rating": null,
        "goals": 0,
        "assists": 0,
        "shots": 1,
        "shotsOnTarget": 0,
        "passes": 46,
        "accuratePasses": 41,
        "touches": 70,
        "xg": 0.01,
        "xa": 0
      },
      {
        "name": "Chris Sleveland",
        "position": "M",
        "jersey": 8,
        "isSub": false,
        "minutes": 90,
        "rating": null,
        "goals": 1,
        "assists": 0,
        "shots": 4,
        "shotsOnTarget": 2,
        "passes": 58,
        "accuratePasses": 45,
        "touches": 73,
        "xg": 0.19,
        "xa": 0.19
      },
      {
        "name": "Jørgen Voilås",
        "position": "M",
        "jersey": 77,
        "isSub": false,
        "minutes": 72,
        "rating": null,
        "goals": 0,
        "assists": 0,
        "shots": 0,
        "shotsOnTarget": 0,
        "passes": 9,
        "accuratePasses": 6,
        "touches": 24,
        "xg": 0,
        "xa": 0.04
      },
      {
        "name": "Justin Salmon",
        "position": "M",
        "jersey": 26,
        "isSub": false,
        "minutes": 90,
        "rating": null,
        "goals": 0,
        "assists": 0,
        "shots": 1,
        "shotsOnTarget": 0,
        "passes": 16,
        "accuratePasses": 11,
        "touches": 26,
        "xg": 0,
        "xa": 0
      },
      {
        "name": "Horenus Zewdu Tadesse",
        "position": "M",
        "jersey": 22,
        "isSub": false,
        "minutes": 77,
        "rating": null,
        "goals": 0,
        "assists": 0,
        "shots": 0,
        "shotsOnTarget": 0,
        "passes": 36,
        "accuratePasses": 30,
        "touches": 51,
        "xg": 0,
        "xa": 0
      },
      {
        "name": "Jack Lahne",
        "position": "M",
        "jersey": 7,
        "isSub": false,
        "minutes": 90,
        "rating": null,
        "goals": 0,
        "assists": 0,
        "shots": 2,
        "shotsOnTarget": 0,
        "passes": 19,
        "accuratePasses": 15,
        "touches": 36,
        "xg": 0.02,
        "xa": 0
      },
      {
        "name": "Joacim Holtan",
        "position": "F",
        "jersey": 99,
        "isSub": false,
        "minutes": 90,
        "rating": null,
        "goals": 0,
        "assists": 0,
        "shots": 0,
        "shotsOnTarget": 0,
        "passes": 13,
        "accuratePasses": 9,
        "touches": 27,
        "xg": 0,
        "xa": 0
      },
      {
        "name": "Adrian Amundsen Bergersen",
        "position": "M",
        "jersey": 11,
        "isSub": true,
        "minutes": 26,
        "rating": null,
        "goals": 0,
        "assists": 0,
        "shots": 0,
        "shotsOnTarget": 0,
        "passes": 6,
        "accuratePasses": 4,
        "touches": 11,
        "xg": 0,
        "xa": 0
      },
      {
        "name": "Sivert Strangstad",
        "position": "M",
        "jersey": 16,
        "isSub": true,
        "minutes": 21,
        "rating": null,
        "goals": 0,
        "assists": 0,
        "shots": 0,
        "shotsOnTarget": 0,
        "passes": 3,
        "accuratePasses": 1,
        "touches": 5,
        "xg": 0,
        "xa": 0
      },
      {
        "name": "Ingvald Sandvik Halgunset",
        "position": "D",
        "jersey": 17,
        "isSub": true,
        "minutes": 13,
        "rating": null,
        "goals": 0,
        "assists": 0,
        "shots": 0,
        "shotsOnTarget": 0,
        "passes": 5,
        "accuratePasses": 2,
        "touches": 8,
        "xg": 0,
        "xa": 0
      },
      {
        "name": "Henrik Elvevold",
        "position": "D",
        "jersey": 15,
        "isSub": true,
        "minutes": 13,
        "rating": null,
        "goals": 0,
        "assists": 0,
        "shots": 0,
        "shotsOnTarget": 0,
        "passes": 2,
        "accuratePasses": 2,
        "touches": 4,
        "xg": 0,
        "xa": 0
      },
      {
        "name": "Mats Viken",
        "position": "G",
        "jersey": 1,
        "isSub": true,
        "minutes": null,
        "rating": null,
        "goals": 0,
        "assists": 0,
        "shots": null,
        "shotsOnTarget": null,
        "passes": null,
        "accuratePasses": null,
        "touches": null,
        "xg": null,
        "xa": null
      },
      {
        "name": "Sammi Davis",
        "position": "D",
        "jersey": 91,
        "isSub": true,
        "minutes": null,
        "rating": null,
        "goals": 0,
        "assists": 0,
        "shots": null,
        "shotsOnTarget": null,
        "passes": null,
        "accuratePasses": null,
        "touches": null,
        "xg": null,
        "xa": null
      },
      {
        "name": "Fanuel Ghebreyohannes Yrga-Alem",
        "position": "D",
        "jersey": 19,
        "isSub": true,
        "minutes": null,
        "rating": null,
        "goals": 0,
        "assists": 0,
        "shots": null,
        "shotsOnTarget": null,
        "passes": null,
        "accuratePasses": null,
        "touches": null,
        "xg": null,
        "xa": null
      },
      {
        "name": "Magnus Sandvik Höiseth",
        "position": "F",
        "jersey": 23,
        "isSub": true,
        "minutes": null,
        "rating": null,
        "goals": 0,
        "assists": 0,
        "shots": null,
        "shotsOnTarget": null,
        "passes": null,
        "accuratePasses": null,
        "touches": null,
        "xg": null,
        "xa": null
      },
      {
        "name": "Jorgen Galta",
        "position": "F",
        "jersey": 9,
        "isSub": true,
        "minutes": null,
        "rating": null,
        "goals": 0,
        "assists": 0,
        "shots": null,
        "shotsOnTarget": null,
        "passes": null,
        "accuratePasses": null,
        "touches": null,
        "xg": null,
        "xa": null
      }
    ],
    "incidents": [
      {
        "minute": 88,
        "addedTime": null,
        "type": "substitution",
        "klass": "regular",
        "player": "Daniel Lysgard",
        "assist": "Mathias Gjerstrom",
        "team": "away",
        "isThisTeam": false
      },
      {
        "minute": 86,
        "addedTime": null,
        "type": "substitution",
        "klass": "regular",
        "player": "Albert Leer Sandstad",
        "assist": "Lucas Haren",
        "team": "away",
        "isThisTeam": false
      },
      {
        "minute": 83,
        "addedTime": null,
        "type": "substitution",
        "klass": "regular",
        "player": "Henrik Elvevold",
        "assist": "Robert Williams",
        "team": "home",
        "isThisTeam": true
      },
      {
        "minute": 83,
        "addedTime": null,
        "type": "substitution",
        "klass": "regular",
        "player": "Ingvald Sandvik Halgunset",
        "assist": "Tord Johnsen Salte",
        "team": "home",
        "isThisTeam": true
      },
      {
        "minute": 76,
        "addedTime": null,
        "type": "substitution",
        "klass": "regular",
        "player": "Sivert Strangstad",
        "assist": "Horenus Zewdu Tadesse",
        "team": "home",
        "isThisTeam": true
      },
      {
        "minute": 71,
        "addedTime": null,
        "type": "substitution",
        "klass": "regular",
        "player": "Adrian Amundsen Bergersen",
        "assist": "Jørgen Voilås",
        "team": "home",
        "isThisTeam": true
      },
      {
        "minute": 66,
        "addedTime": null,
        "type": "substitution",
        "klass": "regular",
        "player": "Oscar Kapskarmo",
        "assist": "Adem Guven",
        "team": "away",
        "isThisTeam": false
      },
      {
        "minute": 65,
        "addedTime": null,
        "type": "card",
        "klass": "yellow",
        "player": "Tord Johnsen Salte",
        "assist": null,
        "team": "home",
        "isThisTeam": true
      },
      {
        "minute": 60,
        "addedTime": null,
        "type": "card",
        "klass": "yellow",
        "player": "Róbert Orri Þorkelsson",
        "assist": null,
        "team": "away",
        "isThisTeam": false
      },
      {
        "minute": 22,
        "addedTime": null,
        "type": "goal",
        "klass": "regular",
        "player": "Jesper Andreas Grundt",
        "assist": "Noa Williams",
        "team": "away",
        "isThisTeam": false
      },
      {
        "minute": 17,
        "addedTime": null,
        "type": "goal",
        "klass": "regular",
        "player": "Chris Sleveland",
        "assist": null,
        "team": "home",
        "isThisTeam": true
      },
      {
        "minute": 9,
        "addedTime": null,
        "type": "card",
        "klass": "yellow",
        "player": "Ludvig Langrekken",
        "assist": null,
        "team": "away",
        "isThisTeam": false
      },
      {
        "minute": 7,
        "addedTime": null,
        "type": "goal",
        "klass": "regular",
        "player": "Jesper Andreas Grundt",
        "assist": "Lucas Haren",
        "team": "away",
        "isThisTeam": false
      }
    ]
  }
]
